zipline/__init__.py
zipline/_utils.py
zipline/_version.py
zipline/cli.py
zipline/py.typed
zipline/zipline.py
zipline_cli-0.3.0.dist-info/licenses/LICENSE
zipline_cli-0.3.0.dist-info/METADATA
zipline_cli-0.3.0.dist-info/WHEEL
zipline_cli-0.3.0.dist-info/entry_points.txt
zipline_cli-0.3.0.dist-info/top_level.txt
zipline_cli-0.3.0.dist-info/RECORD
