Metadata-Version: 2.4
Name: zipline-cli
Version: 0.3.0
Summary: Python 3 CLI File Uploader for Diced/Zipline v3/v4 Upload Server and Django Files.
Author: Shane
License: MIT License
Project-URL: Changelog, https://github.com/cssnr/zipline-cli/releases
Project-URL: Discord, https://discord.gg/wXy6m2X8wY
Project-URL: Documentation, https://zipline-cli.cssnr.com/
Project-URL: Funding, https://ko-fi.com/cssnr
Project-URL: GitHub, https://github.com/cssnr/zipline-cli
Project-URL: Homepage, https://cssnr.com/
Project-URL: Issues, https://github.com/cssnr/zipline-cli/issues
Classifier: License :: OSI Approved :: MIT License
Classifier: Natural Language :: English
Classifier: Operating System :: OS Independent
Classifier: Programming Language :: Python
Classifier: Programming Language :: Python :: 3
Classifier: Programming Language :: Python :: 3 :: Only
Classifier: Topic :: Communications :: File Sharing
Classifier: Topic :: Terminals
Classifier: Typing :: Typed
Requires-Python: >=3.9
License-File: LICENSE
Requires-Dist: python-dotenv
Requires-Dist: requests<3,>=2
Requires-Dist: typer
Dynamic: license-file
